README.md
setup.py
pyatool/__init__.py
pyatool/adb.py
pyatool/binder.py
pyatool/config.py
pyatool/core.py
pyatool/extras.py
pyatool/logger.py
pyatool.egg-info/PKG-INFO
pyatool.egg-info/SOURCES.txt
pyatool.egg-info/dependency_links.txt
pyatool.egg-info/requires.txt
pyatool.egg-info/top_level.txt