Metadata-Version: 1.0
Name: pyatool
Version: 0.3.3
Summary: python android toolkit
Home-page: https://github.com/williamfzc/pyatool
Author: williamfzc
Author-email: fengzc@vip.qq.com
License: UNKNOWN
Platform: UNKNOWN
